[
  {
    "children": [],
    "icon": "mdi-view-dashboard",
    "id": 1,
    "name": "Dashboard",
    "name_en": "Dashboard",
    "url": "/dashboard"
  },
  {
    "children": [],
    "icon": "mdi-view-dashboard",
    "id": 2,
    "name": "Dashboard",
    "name_en": "Dashboard",
    "url": "/dashboard-edu"
  },
  {
    "children": [],
    "icon": "mdi-view-dashboard",
    "id": 3,
    "name": "3D監控模式",
    "name_en": "3D Monitoring Mode",
    "url": "/dashboard-3d"
  },
  {
    "children": [],
    "icon": "mdi-file",
    "id": 4,
    "name": "已結案事件單",
    "name_en": "Closed Case List",
    "url": "/closed-case-list"
  },
  {
    "children": [
      {
        "children": [],
        "id": 6,
        "name": "維運團隊",
        "name_en": "Maintenance Team",
        "url": "/contact-information/maintenance-team"
      },
      {
        "children": [],
        "id": 7,
        "name": "GigaPoPs",
        "name_en": "GigaPoPs",
        "url": "/contact-information/gigapops"
      },
      {
        "children": [],
        "id": 8,
        "name": "連線單位",
        "name_en": "Connection Unit",
        "url": "/contact-information/connection-unit"
      },
      {
        "children": [],
        "id": 9,
        "name": "VPLS VPN",
        "name_en": "VPLS VPN",
        "url": "/contact-information/vpls-vpn"
      },
      {
        "children": [],
        "id": 10,
        "name": "國內外BGP Peering",
        "name_en": "Domestic and International BGP Peering",
        "url": "/contact-information/domestic-and-international-bgp-peering"
      }
    ],
    "icon": "mdi-file",
    "id": 5,
    "name": "聯絡資料",
    "name_en": "Contact Information",
    "url": "/contact-information"
  },
  {
    "children": [
      {
        "children": [],
        "id": 12,
        "name": "設備資料設定檔",
        "name_en": "Device Data Setting File",
        "url": "/device-info/device-data-setting"
      }
    ],
    "icon": "mdi-file",
    "id": 11,
    "name": "設備資料",
    "name_en": "Device Information",
    "url": "/device-info"
  },
  {
    "children": [
      {
        "children": [
          {
            "id": 15,
            "name": "國內骨幹流量狀況",
            "name_en": "Domestic Backbone Traffic Status",
            "url": "/monitor/circuit-status/domestic-backbone-traffic"
          },
          {
            "id": 16,
            "name": "國內骨幹界接介面狀況",
            "name_en": "Domestic Backbone Interface Status",
            "url": "/monitor/circuit-status/domestic-backbone-interface"
          },
          {
            "id": 17,
            "name": "國際電路流量狀況",
            "name_en": "International Circuit Traffic Status",
            "url": "/monitor/circuit-status/international-circuit-traffic"
          },
          {
            "id": 18,
            "name": "國際電路界接介面狀況",
            "name_en": "International Circuit Interface Status",
            "url": "/monitor/circuit-status/international-circuit-interface"
          },
          {
            "id": 19,
            "name": "國際電路界接介面WAN Port IP Ping 狀況",
            "name_en": "International Circuit WAN Port IP Ping Status",
            "url": "/monitor/circuit-status/international-circuit-wan-ping"
          },
          {
            "id": 20,
            "name": "國科會線路狀況",
            "name_en": "NSTC Line Status",
            "url": "/monitor/circuit-status/nstc-line-status"
          },
          {
            "id": 21,
            "name": "資策會線路界接介面狀況",
            "name_en": "III Line Interface Status",
            "url": "/monitor/circuit-status/iii-line-interface"
          },
          {
            "id": 22,
            "name": "TWNIC DNS 代管 Server 界接介面狀況",
            "name_en": "TWNIC DNS Server Interface Status",
            "url": "/monitor/circuit-status/twnic-dns-server-interface"
          },
          {
            "id": 23,
            "name": "國內骨幹電路介面品質",
            "name_en": "Domestic Backbone Interface Quality",
            "url": "/monitor/circuit-status/domestic-backbone-interface-quality"
          }
        ],
        "id": 14,
        "name": "電路狀態",
        "name_en": "Circuit Status",
        "url": "/monitor/circuit-status"
      },
      {
        "children": [
          {
            "id": 25,
            "name": "設備CPU狀況",
            "name_en": "Device CPU Status",
            "url": "/monitor/device-status/cpu-status"
          },
          {
            "id": 26,
            "name": "設備Memory狀況",
            "name_en": "Device Memory Status",
            "url": "/monitor/device-status/memory-status"
          },
          {
            "id": 27,
            "name": "設備Power Supply狀況",
            "name_en": "Device Power Supply Status",
            "url": "/monitor/device-status/power-supply-status"
          },
          {
            "id": 85,
            "name": "設備風扇狀況",
            "name_en": "Device Fan Status",
            "url": "/monitor/device-status/fan-status"
          },
          {
            "id": 28,
            "name": "骨幹設備IP Ping狀況",
            "name_en": "Backbone Device IP Ping Status",
            "url": "/monitor/device-status/backbone-ip-ping-status"
          },
          {
            "id": 29,
            "name": "局端與納管設備OOB IP Ping 狀況",
            "name_en": "OOB IP Ping Status for Local and Managed Devices",
            "url": "/monitor/device-status/oob-ip-ping-status"
          },
          {
            "id": 30,
            "name": "機房電源設備與溫控設備IP Ping 狀況",
            "name_en": "Data Center Power and Temperature Control Equipment IP Ping Status",
            "url": "/monitor/device-status/data-center-ip-ping-status"
          },
          {
            "id": 86,
            "name": "光傳輸元件監控狀況",
            "name_en": "Optical Transmission Device Monitoring Status",
            "url": "/monitor/device-status/optical-transmission-device-monitoring-status"
          }
        ],
        "id": 24,
        "name": "設備狀態",
        "name_en": "Device Status",
        "url": "/monitor/device-status"
      },
      {
        "children": [
          {
            "children": [],
            "id": 32,
            "name": "VPN Client界接介面狀況",
            "name_en": "VPN Client Interface Status",
            "url": "/monitor/vpls-vpn-status/vpn-client-interface-status"
          },
          {
            "children": [],
            "id": 33,
            "name": "VPLS VPN Peer狀況",
            "name_en": "VPLS VPN Peer Status",
            "url": "/monitor/vpls-vpn-status/vpls-vpn-peer-status"
          },
          {
            "children": [],
            "id": 84,
            "name": "VPLS VPN界接介面Port IP Ping狀況",
            "name_en": "VPLS VPN Interface Port IP Ping Status",
            "url": "/monitor/vpls-vpn-status/vpls-vpn-interface-port-ip-ping-status"
          }
        ],
        "id": 31,
        "name": "VPLS VPN狀態",
        "name_en": "VPLS VPN Status",
        "url": "/monitor/vpls-vpn-status"
      },
      {
        "children": [
          {
            "children": [],
            "id": 35,
            "name": "機房溫度狀況",
            "name_en": "Server Room Temperature Status",
            "url": "/monitor/server-room-status/room-temperature-status"
          },
          {
            "children": [],
            "id": 36,
            "name": "主節點SMR電壓與電流狀況",
            "name_en": "Main Node SMR Voltage and Current Status",
            "url": "/monitor/server-room-status/main-node-smr-voltage-current-status"
          },
          {
            "children": [],
            "id": 37,
            "name": "RPM總負載電流狀況",
            "name_en": "RPM Total Load Current Status",
            "url": "/monitor/server-room-status/rpm-total-load-current-status"
          },
          {
            "children": [],
            "id": 87,
            "name": "PDU總負載電流狀況",
            "name_en": "PDU Total Load Current Status",
            "url": "/monitor/server-room-status/pdu-total-load-current-status"
          },
          {
            "children": [],
            "id": 88,
            "name": "UPS不斷電系統狀況",
            "name_en": "UPS Uninterruptible Power Supply Status",
            "url": "/monitor/server-room-status/ups-uninterruptible-power-supply-status"
          }
        ],
        "id": 34,
        "name": "機房環境狀態",
        "name_en": "Server Room Status",
        "url": "/monitor/server-room-status"
      },
      {
        "children": [
          {
            "children": [],
            "id": 39,
            "name": "連線單位WAN Port Ping 狀況",
            "name_en": "Connection Unit WAN Port Ping Status",
            "url": "/monitor/connection-unit-status/wan-port-ping-status"
          },
          {
            "children": [],
            "id": 40,
            "name": "連線單位路由狀況",
            "name_en": "Connection Unit Routing Status",
            "url": "/monitor/connection-unit-status/routing-status"
          },
          {
            "children": [],
            "id": 41,
            "name": "連線單位流量狀況",
            "name_en": "Connection Unit Traffic Status",
            "url": "/monitor/connection-unit-status/traffic-status"
          }
        ],
        "id": 38,
        "name": "連線單位狀態",
        "name_en": "Connection Unit Status",
        "url": "/monitor/connection-unit-status"
      },
      {
        "children": [
          {
            "children": [],
            "id": 43,
            "name": "BGP Peering狀況",
            "name_en": "BGP Peering Status",
            "url": "/monitor/bgp-peering-status/peering-bgp-status"
          },
          {
            "children": [],
            "id": 44,
            "name": "RR BGP狀況",
            "name_en": "RR BGP Status",
            "url": "/monitor/bgp-peering-status/rr-bgp-status"
          }
        ],
        "id": 42,
        "name": "BGP Peering狀態",
        "name_en": "BGP Peering Status",
        "url": "/monitor/bgp-peering-status"
      },
      {
        "children": [
          {
            "children": [],
            "id": 46,
            "name": "SSL VPN狀況",
            "name_en": "SSL VPN Status",
            "url": "/monitor/ssl-vpn-status/ssl-vpn-status"
          }
        ],
        "id": 45,
        "name": "SSL VPN狀態",
        "name_en": "SSL VPN Status",
        "url": "/monitor/ssl-vpn-status"
      },
      {
        "children": [],
        "id": 82,
        "name": "關聯式分析",
        "name_en": "Correlation Analysis",
        "url": "/monitor/correlation-analysis"
      }
    ],
    "icon": "mdi-monitor",
    "id": 13,
    "name": "監控狀況",
    "name_en": "Monitoring Status",
    "url": "/monitor"
  },
  {
    "children": [
      {
        "children": [],
        "id": 48,
        "name": "異常事件紀錄",
        "name_en": "Abnormal Event Record",
        "url": "/record-search/abnormal-event-record"
      },
      {
        "children": [],
        "id": 49,
        "name": "日誌記錄查詢",
        "name_en": "Log Record",
        "url": "/record-search/log-record"
      }
    ],
    "icon": "mdi-file",
    "id": 47,
    "name": "記錄查詢",
    "name_en": "Record Search",
    "url": "/record-search"
  },
  {
    "children": [
      {
        "children": [],
        "id": 52,
        "name": "100G維運報表查詢",
        "name_en": "100G Maintenance Report Query",
        "url": "/report-search/100G-maintenance-report-query"
      },
      {
        "children": [
          {
            "children": [],
            "id": 73,
            "name": "連線單位最近三個月流出入比較圖(Top10)",
            "name_en": "Comparison of Flow In and Out in the Last Three Months by Connection Unit(Top10)",
            "url": "/report-search/international-circuit-report-query/flow-comparison"
          },
          {
            "children": [],
            "id": 74,
            "name": "美國電路-依照連線單位，最近一個月流出入圓餅圖(Top10)",
            "name_en": "US Circuits - Flow In and Out Pie Chart by Connection Unit in the Last Month(Top10)",
            "url": "/report-search/international-circuit-report-query/us-circuits"
          },
          {
            "children": [],
            "id": 75,
            "name": "美國電路各年度每月之流出入比較趨勢圖",
            "name_en": "Comparison Trend Chart of Monthly Flow In and Out for Each Year in US Circuits",
            "url": "/report-search/international-circuit-report-query/us-circuits-trend"
          },
          {
            "children": [],
            "id": 76,
            "name": "連線單位歷年出入比較圖(Top10)",
            "name_en": "Comparison Chart of Flow In and Out Over the Years by Connection Unit(Top10)",
            "url": "/report-search/international-circuit-report-query/connection-comparison"
          },
          {
            "children": [],
            "id": 77,
            "name": "美國電路-依照連線單位，年度流出入圓餅圖(Top10)",
            "name_en": "US Circuits - Flow In and Out Pie Chart by Connection Unit Annually (Top10)",
            "url": "/report-search/international-circuit-report-query/us-circuits-connection"
          }
        ],
        "id": 53,
        "name": "國際電路報表查詢",
        "name_en": "International Circuit Report Query",
        "url": "/report-search/international-circuit-report-query"
      }
    ],
    "icon": "mdi-file",
    "id": 51,
    "name": "報表查詢",
    "name_en": "Report Search",
    "url": "/report-search"
  },
  {
    "children": [
      {
        "children": [
          {
            "children": [],
            "id": 56,
            "name": "維運團隊管理",
            "name_en": "Operation Team Management",
            "url": "/monitoring-item-management/data-management/operation-team-management"
          },
          {
            "children": [],
            "id": 57,
            "name": "GigaPops管理",
            "name_en": "GigaPoPs Management",
            "url": "/monitoring-item-management/data-management/gigapops-management"
          },
          {
            "children": [],
            "id": 58,
            "name": "連線單位管理",
            "name_en": "Connection Unit Management",
            "url": "/monitoring-item-management/data-management/connection-unit-management"
          },
          {
            "children": [],
            "id": 59,
            "name": "BGP Peering管理",
            "name_en": "BGP Peering Management",
            "url": "/monitoring-item-management/data-management/bgp-peering-management"
          },
          {
            "children": [
              {
                "children": [],
                "id": 83,
                "name": "VPLS VPN界接介面資料維護",
                "name_en": "VPLS VPN Interface Management",
                "url": "/monitoring-item-management/data-management/vpls-vpn-management"
              }
            ],
            "id": 60,
            "name": "VPLS VPN管理",
            "name_en": "VPLS VPN Management",
            "url": "/monitoring-item-management/data-management/vpls-vpn-management"
          },
          {
            "children": [
              {
                "id": 62,
                "name": "國內電路",
                "name_en": "Domestic Circuit",
                "url": "/monitoring-item-management/data-management/circuit-interface-management/domestic-circuit"
              },
              {
                "id": 63,
                "name": "國際電路",
                "name_en": "International Circuit",
                "url": "/monitoring-item-management/data-management/circuit-interface-management/internation-circuit"
              },
              {
                "id": 64,
                "name": "資策會監控電路",
                "name_en": "Institute for Information Industry Monitoring Circuit",
                "url": "/monitoring-item-management/data-management/circuit-interface-management/iii-circuit"
              }
            ],
            "id": 61,
            "name": "電路介面管理",
            "name_en": "Circuit Interface Management",
            "url": "/monitoring-item-management/data-management/circuit-interface-management"
          },
          {
            "children": [],
            "id": 65,
            "name": "帳號管理",
            "name_en": "Account Management",
            "url": "/monitoring-item-management/data-management/account-management"
          },
          {
            "children": [],
            "id": 66,
            "name": "群組授權管理",
            "name_en": "Group Management",
            "url": "/monitoring-item-management/data-management/group-management"
          },
          {
            "children": [],
            "id": 67,
            "name": "系統參數設定",
            "name_en": "System Parameter",
            "url": "/monitoring-item-management/data-management/system-parameter-management"
          }
        ],
        "id": 55,
        "name": "資料管理",
        "name_en": "Data Management",
        "url": "/monitoring-item-management/data-management"
      },
      {
        "children": [
          {
            "children": [],
            "id": 69,
            "name": "連線單位",
            "name_en": "Connection Unit",
            "url": "/monitoring-item-management/alert-management/connection-unit"
          },
          {
            "children": [],
            "id": 70,
            "name": "BGP Peering",
            "url": "/monitoring-item-management/alert-management/bgp-peering"
          },
          {
            "children": [],
            "id": 71,
            "name": "事件類別",
            "name_en": "Event Category",
            "url": "/monitoring-item-management/alert-management/event-category"
          },
          {
            "children": [],
            "id": 72,
            "name": "設備類",
            "name_en": "Equipment Category",
            "url": "/monitoring-item-management/alert-management/equipment-category"
          }
        ],
        "id": 68,
        "name": "告警管理",
        "name_en": "Alert Management",
        "url": "/monitoring-item-management/alert-management"
      },
      {
        "children": [],
        "id": 81,
        "name": "網路流量拓樸圖管理",
        "name_en": "Topological Management",
        "url": "/monitoring-item-management/topological-management"
      },
      {
        "children": [],
        "id": 89,
        "name": "溫溼度感應器管理",
        "name_en": "Temperature and Humidity Sensor Management",
        "url": "/monitoring-item-management/temperature-and-humidity-sensor-management"
      },
      {
        "children": [],
        "id": 90,
        "name": "PDU智慧排插管理",
        "name_en": "PDU Smart Power Strip Management",
        "url": "/monitoring-item-management/pdu-smart-power-strip-management"
      },
      {
        "children": [],
        "id": 91,
        "name": "UPS不斷電系統管理",
        "name_en": "UPS Uninterruptible Power System Management",
        "url": "/monitoring-item-management/ups-uninterruptible-power-system-management"
      },
      {
        "children": [],
        "id": 87,
        "name": "光傳輸元件監控管理",
        "name_en": "Optical Transmission Device Monitoring and Management",
        "url": "/monitoring-item-management/optical-transmission-device-monitoring-and-management"
      },
      {
        "children": [
          {
            "children": [],
            "id": 86,
            "name": "VPLS VPN界接介面狀況維護管理",
            "name_en": "VPLS VPN Interface Status Maintenance Management",
            "url": "/monitoring-item-management/vpls-vpn-management/vpls-vpn-interface-status-maintenance-management"
          }
        ],
        "id": 85,
        "name": "VPLS VPN管理",
        "name_en": "VPLS VPN Management",
        "url": "/monitoring-item-management/vpls-vpn-management"
      }
    ],
    "id": 54,
    "name": "監控項目管理",
    "name_en": "Monitoring Item Management",
    "url": "/monitoring-item-management"
  },
  {
    "children": [
      {
        "children": [],
        "hidden": true,
        "id": 79,
        "name": "新增工單",
        "name_en": "Add Work Order",
        "url": "/work-order-management/add"
      }
    ],
    "id": 78,
    "name": "工單管理",
    "name_en": "Work Order Management",
    "url": "/work-order-management"
  },
  {
    "children": [],
    "id": 80,
    "name": "設備組態",
    "name_en": "Device Configuration",
    "url": "/device-configuration"
  }
]
